SeleCrawler/__init__.py
SeleCrawler/selenium_controller.py
SeleCrawler-0.0.2.dist-info/METADATA
SeleCrawler-0.0.2.dist-info/WHEEL
SeleCrawler-0.0.2.dist-info/top_level.txt
SeleCrawler-0.0.2.dist-info/RECORD
